streamscrobbler/__init__.py
streamscrobbler/streamscrobbler.py
streamscrobbler3-0.0.4.dist-info/LICENSE
streamscrobbler3-0.0.4.dist-info/METADATA
streamscrobbler3-0.0.4.dist-info/WHEEL
streamscrobbler3-0.0.4.dist-info/top_level.txt
streamscrobbler3-0.0.4.dist-info/RECORD
